Metadata-Version: 2.1
Name: PhiSpy
Version: 4.2.18
Summary: Prophage finder using multiple metrics
Home-page: https://github.com/linsalrob/PhiSpy
Author: Rob Edwards
Author-email: raedwards@gmail.com
License: The MIT License (MIT)
Keywords: phage prophage bioinformatics microbiology bacteria genome genomics
Platform: any
Classifier: Development Status :: 4 - Beta
Classifier: Intended Audience :: Science/Research
Classifier: License :: OSI Approved :: MIT License
Classifier: Natural Language :: English
Classifier: Operating System :: MacOS :: MacOS X
Classifier: Operating System :: POSIX :: Linux
Classifier: Operating System :: Unix
Classifier: Programming Language :: Python :: 3.0
Classifier: Topic :: Scientific/Engineering :: Bio-Informatics
